{
  "_id": "page.identity-documents-data-subject",
  "_type": "page.form",
  "components": [
    {
      "_id": "page.identity-documents-data-subject--upload.auto_name__16",
      "_type": "upload",
      "hint": "This can be a copy of their driving licence or passport. Maximum size: 7MB per file",
      "label": "Photo ID",
      "name": "auto_name__16"
    },
    {
      "_id": "page.identity-documents-data-subject--upload.auto_name__17",
      "_type": "upload",
      "hint": "This can be a copy of a bill in your name and dated within the last 3 months (For example an electricity bill or council tax bill). Maximum file size: 7MB",
      "label": "Proof of address",
      "name": "auto_name__17"
    }
  ],
  "heading": "Upload ID documents for the person you are requesting information about",
  "show": {
    "identifier": "auto_name__15",
    "operator": "is",
    "value": "auto_value__2"
  },
  "steps": [
    "page.person-in-custody_identity-documents-data-subject-check"
  ],
  "url": "identity-documents-data-subject"
}